install_party/__init__.py
install_party/__main__.py
install_party/creator/__init__.py
install_party/creator/create.py
install_party/dns/__init__.py
install_party/dns/dns_provider.py
install_party/dns/dns_provider_client.py
install_party/dns/providers/__init__.py
install_party/dns/providers/ovh.py
install_party/eraser/__init__.py
install_party/eraser/delete.py
install_party/instances/__init__.py
install_party/instances/instances_provider.py
install_party/instances/instances_provider_client.py
install_party/instances/providers/__init__.py
install_party/instances/providers/openstack.py
install_party/lister/__init__.py
install_party/lister/list.py
install_party/scripts/post_create.sh
install_party/util/__init__.py
install_party/util/entry.py
install_party/util/errors.py
install_party-1.0.0.dist-info/LICENSE
install_party-1.0.0.dist-info/METADATA
install_party-1.0.0.dist-info/WHEEL
install_party-1.0.0.dist-info/top_level.txt
install_party-1.0.0.dist-info/RECORD
