Metadata-Version: 2.1
Name: install-party
Version: 1.0.0
Summary: Instantiate and manage hosts for Matrix homeserver install parties
Home-page: https://github.com/babolivier/install-party
Author: Brendan Abolivier
Author-email: babolivier@matrix.org
License: UNKNOWN
Platform: UNKNOWN
Classifier: Programming Language :: Python :: 3.6
Classifier: Programming Language :: Python :: 3.7
Classifier: License :: OSI Approved :: GNU General Public License v3 (GPLv3)
Classifier: Operating System :: OS Independent
Requires-Python: >=3.6
Requires-Dist: ovh (==0.5.0)
Requires-Dist: python-novaclient (==15.1.0)
Requires-Dist: PyYAML (==5.1.2)
Requires-Dist: requests (==2.22.0)
Requires-Dist: tabulate (==0.8.5)
